{
  "elements/pages/pa-buttons/pa-buttons.html": {
    "shared_bundle_1.html": {
      "type": "document",
      "weight": 1
    }
  },
  "elements/pages/pa-charts/pa-charts.html": {
    "shared_bundle_1.html": {
      "type": "document",
      "weight": 1
    }
  },
  "elements/pages/pa-dashboard/pa-dashboard.html": {
    "shared_bundle_1.html": {
      "type": "document",
      "weight": 1
    }
  },
  "elements/pages/pa-form-elements/pa-form-elements.html": {
    "shared_bundle_1.html": {
      "type": "document",
      "weight": 1
    }
  },
  "elements/pages/pa-maps/pa-maps.html": {
    "shared_bundle_1.html": {
      "type": "document",
      "weight": 1
    }
  },
  "elements/pages/pa-not-found/pa-not-found.html": {
    "shared_bundle_1.html": {
      "type": "document",
      "weight": 1
    }
  },
  "elements/pages/pa-profile/pa-profile.html": {
    "shared_bundle_1.html": {
      "type": "document",
      "weight": 1
    }
  },
  "elements/pages/pa-tables/pa-tables.html": {
    "shared_bundle_1.html": {
      "type": "document",
      "weight": 1
    }
  },
  "elements/pages/pa-typo/pa-typo.html": {
    "shared_bundle_1.html": {
      "type": "document",
      "weight": 1
    }
  },
  "elements/pages/pa-ui-other/pa-ui-other.html": {
    "shared_bundle_1.html": {
      "type": "document",
      "weight": 1
    }
  },
  "index.html": {
    "scripts/jquery-3.2.1.min.js": {
      "type": "script",
      "weight": 1
    },
    "bower_components/webcomponentsjs/webcomponents-lite.js": {
      "type": "script",
      "weight": 1
    },
    "elements/elements.html": {
      "type": "document",
      "weight": 1
    },
    "styles/app-theme.html": {
      "type": "document",
      "weight": 1
    },
    "styles/shared-styles.html": {
      "type": "document",
      "weight": 1
    },
    "elements/splash-screen.html": {
      "type": "document",
      "weight": 1
    },
    "elements/common/pa-menu.html": {
      "type": "document",
      "weight": 1
    },
    "elements/common/pa-pages.html": {
      "type": "document",
      "weight": 1
    },
    "elements/common/pa-search.html": {
      "type": "document",
      "weight": 1
    },
    "elements/common/pa-simple-grid.html": {
      "type": "document",
      "weight": 1
    },
    "elements/common/pa-page-title.html": {
      "type": "document",
      "weight": 1
    },
    "elements/common/pa-auth/pa-auth-data.html": {
      "type": "document",
      "weight": 1
    },
    "elements/common/pa-auth/pa-auth-info.html": {
      "type": "document",
      "weight": 1
    },
    "elements/common/pa-auth/pa-auth-profile-dialog.html": {
      "type": "document",
      "weight": 1
    },
    "elements/common/pa-footer.html": {
      "type": "document",
      "weight": 1
    },
    "elements/common/pa-widgets/pa-widgets.html": {
      "type": "document",
      "weight": 1
    },
    "elements/common/pa-widgets/pa-widget.html": {
      "type": "document",
      "weight": 1
    },
    "elements/pages/pa-charts/pa-charts.html": {
      "type": "document",
      "weight": 1
    },
    "shared_bundle_1.html": {
      "type": "document",
      "weight": 1
    },
    "elements/pages/pa-dashboard/pa-dashboard.html": {
      "type": "document",
      "weight": 1
    },
    "elements/pages/pa-form-elements/pa-form-elements.html": {
      "type": "document",
      "weight": 1
    },
    "elements/pages/pa-maps/pa-maps.html": {
      "type": "document",
      "weight": 1
    },
    "elements/pages/pa-tables/pa-tables.html": {
      "type": "document",
      "weight": 1
    },
    "elements/pages/pa-buttons/pa-buttons.html": {
      "type": "document",
      "weight": 1
    },
    "elements/pages/pa-ui-other/pa-ui-other.html": {
      "type": "document",
      "weight": 1
    },
    "elements/pages/pa-typo/pa-typo.html": {
      "type": "document",
      "weight": 1
    },
    "elements/pages/pa-profile/pa-profile.html": {
      "type": "document",
      "weight": 1
    },
    "elements/pages/pa-not-found/pa-not-found.html": {
      "type": "document",
      "weight": 1
    },
    "elements/games/games-list-style.html": {
      "type": "document",
      "weight": 1
    },
    "elements/games/games-list.html": {
      "type": "document",
      "weight": 1
    },
    "scripts/app.js": {
      "type": "script",
      "weight": 1
    }
  }
}